kodak/__about__.py
kodak/__init__.py
kodak/__main__.py
kodak/_server.py
kodak/application.py
kodak/cli.py
kodak/configuration.py
kodak/constants.py
kodak/database/__init__.py
kodak/database/_shared.py
kodak/database/access.py
kodak/database/image.py
kodak/database/manip.py
kodak/exceptions.py
kodak/index.py
kodak/manipulations.py
kodak/openapi.yaml
kodak/py.typed
kodak/resources/__init__.py
kodak/resources/_shared.py
kodak/resources/heartbeat.py
kodak/resources/image.py
kodak/resources/manip.py
kodak/resources/openapi.py
kodak-0.1.0.dist-info/entry_points.txt
kodak-0.1.0.dist-info/LICENSE.md
kodak-0.1.0.dist-info/WHEEL
kodak-0.1.0.dist-info/METADATA
kodak-0.1.0.dist-info/RECORD
