Metadata-Version: 2.1
Name: kodak
Version: 0.1.0
Summary: HTTP server for uploading images and generating thumbnails
Home-page: https://github.com/enpaul/kodak/
License: MIT
Keywords: flask,image,thumbnail,hosting
Author: Ethan Paul
Author-email: 24588726+enpaul@users.noreply.github.com
Requires-Python: >=3.7,<4.0
Classifier: Development Status :: 2 - Pre-Alpha
Classifier: Environment :: Web Environment
Classifier: Framework :: Flask
Classifier: Intended Audience :: Developers
Classifier: Intended Audience :: Information Technology
Classifier: Intended Audience :: System Administrators
Classifier: License :: OSI Approved :: MIT License
Classifier: Natural Language :: English
Classifier: Operating System :: OS Independent
Classifier: Operating System :: POSIX :: Linux
Classifier: Programming Language :: Python :: 3
Classifier: Programming Language :: Python :: 3.10
Classifier: Programming Language :: Python :: 3.7
Classifier: Programming Language :: Python :: 3.8
Classifier: Programming Language :: Python :: 3.9
Classifier: Programming Language :: Python :: Implementation :: CPython
Classifier: Topic :: Internet :: WWW/HTTP
Classifier: Topic :: Internet :: WWW/HTTP :: Dynamic Content
Classifier: Topic :: Multimedia :: Graphics
Classifier: Topic :: Multimedia :: Graphics :: Graphics Conversion
Provides-Extra: deployment
Requires-Dist: Pillow (>=8.3.2,<9.0.0)
Requires-Dist: flask (>=1.1.2,<2.0.0)
Requires-Dist: flask-restful (>=0.3.8,<0.4.0)
Requires-Dist: gunicorn (>=20.1.0,<21.0.0); extra == "deployment"
Requires-Dist: peewee (>=3.13.3,<4.0.0)
Requires-Dist: ruamel.yaml (>=0.16.12,<0.17.0)
Project-URL: Repository, https://github.com/enpaul/kodak/
